cnspy_trajectory_evaluation/AbsoluteTrajectoryError.py
cnspy_trajectory_evaluation/AlignedTrajectories.py
cnspy_trajectory_evaluation/AssociatedTrajectories.py
cnspy_trajectory_evaluation/DifferentialTrajectoryError.py
cnspy_trajectory_evaluation/EstimationTrajectoryError.py
cnspy_trajectory_evaluation/EvaluationReport.py
cnspy_trajectory_evaluation/NEES.py
cnspy_trajectory_evaluation/SpatialAlignment.py
cnspy_trajectory_evaluation/TrajectoryANEES.py
cnspy_trajectory_evaluation/TrajectoryAlignmentTypes.py
cnspy_trajectory_evaluation/TrajectoryEvaluation.py
cnspy_trajectory_evaluation/TrajectoryEvaluationTool.py
cnspy_trajectory_evaluation/TrajectoryPosOrientNEES.py
cnspy_trajectory_evaluation/TrajectoryPoseNEES.py
cnspy_trajectory_evaluation/__init__.py
test/__init__.py
test/pandas_test.py
test/test_AbsoluteTrajectoryError.py
test/test_AlignedTrajectories.py
test/test_DifferentialTrajectoryError.py
test/test_EvaluationReport.py
test/test_OV_TrajectoryEvaluation.py
test/test_TrajectoryANEES.py
test/test_TrajectoryEvaluation.py
test/test_TrajectoryPosOrientNEES.py
cnspy_trajectory_evaluation-0.2.7.dist-info/LICENCE
cnspy_trajectory_evaluation-0.2.7.dist-info/METADATA
cnspy_trajectory_evaluation-0.2.7.dist-info/WHEEL
cnspy_trajectory_evaluation-0.2.7.dist-info/entry_points.txt
cnspy_trajectory_evaluation-0.2.7.dist-info/top_level.txt
cnspy_trajectory_evaluation-0.2.7.dist-info/RECORD
